pyasic/__init__.py
pyasic/config/__init__.py
pyasic/config/base.py
pyasic/config/fans.py
pyasic/config/frequency.py
pyasic/config/mining/__init__.py
pyasic/config/mining/algo.py
pyasic/config/mining/presets.py
pyasic/config/mining/scaling.py
pyasic/config/pools.py
pyasic/config/temperature.py
pyasic/data/__init__.py
pyasic/data/boards.py
pyasic/data/device.py
pyasic/data/error_codes/X19.py
pyasic/data/error_codes/__init__.py
pyasic/data/error_codes/base.py
pyasic/data/error_codes/bos.py
pyasic/data/error_codes/innosilicon.py
pyasic/data/error_codes/vnish.py
pyasic/data/error_codes/whatsminer.py
pyasic/data/fans.py
pyasic/data/pools.py
pyasic/device/__init__.py
pyasic/device/algorithm/__init__.py
pyasic/device/algorithm/base.py
pyasic/device/algorithm/blake256.py
pyasic/device/algorithm/blockflow.py
pyasic/device/algorithm/eaglesong.py
pyasic/device/algorithm/equihash.py
pyasic/device/algorithm/ethash.py
pyasic/device/algorithm/handshake.py
pyasic/device/algorithm/hashrate/__init__.py
pyasic/device/algorithm/hashrate/base.py
pyasic/device/algorithm/hashrate/blake256.py
pyasic/device/algorithm/hashrate/blockflow.py
pyasic/device/algorithm/hashrate/eaglesong.py
pyasic/device/algorithm/hashrate/equihash.py
pyasic/device/algorithm/hashrate/ethash.py
pyasic/device/algorithm/hashrate/handshake.py
pyasic/device/algorithm/hashrate/kadena.py
pyasic/device/algorithm/hashrate/kheavyhash.py
pyasic/device/algorithm/hashrate/scrypt.py
pyasic/device/algorithm/hashrate/sha256.py
pyasic/device/algorithm/hashrate/unit/__init__.py
pyasic/device/algorithm/hashrate/unit/base.py
pyasic/device/algorithm/hashrate/unit/blake256.py
pyasic/device/algorithm/hashrate/unit/blockflow.py
pyasic/device/algorithm/hashrate/unit/eaglesong.py
pyasic/device/algorithm/hashrate/unit/equihash.py
pyasic/device/algorithm/hashrate/unit/ethash.py
pyasic/device/algorithm/hashrate/unit/handshake.py
pyasic/device/algorithm/hashrate/unit/kadena.py
pyasic/device/algorithm/hashrate/unit/kheavyhash.py
pyasic_umhost-0.2.0.dist-info/METADATA
pyasic_umhost-0.2.0.dist-info/WHEEL
pyasic_umhost-0.2.0.dist-info/licenses/LICENSE.txt
pyasic_umhost-0.2.0.dist-info/RECORD
