Metadata-Version: 2.4
Name: pyasic-umhost
Version: 0.2.0
Summary: A simplified and standardized interface for Bitcoin ASICs.
License: Apache 2.0
License-File: LICENSE.txt
Keywords: python,asic,bitcoin,whatsminer,antminer,braiins-os,vnish,luxos
Author: UpstreamData
Author-email: brett@upstreamdata.ca
Requires-Python: >3.10, <4.0
Classifier: Development Status :: 4 - Beta
Classifier: Intended Audience :: Developers
Classifier: License :: OSI Approved :: Apache Software License
Classifier: Programming Language :: Python
Classifier: Programming Language :: Python :: 3
Classifier: Programming Language :: Python :: 3.9
Classifier: Programming Language :: Python :: 3.10
Classifier: Programming Language :: Python :: 3.11
Classifier: Programming Language :: Python :: 3.12
Classifier: Programming Language :: Python :: 3.13
Requires-Dist: aiofiles (>=23.2.1)
Requires-Dist: asyncssh (>=2.20.0)
Requires-Dist: betterproto (==2.0.0b7)
Requires-Dist: cryptography (>=39.0)
Requires-Dist: httpx (>=0.26.0)
Requires-Dist: passlib (>=1.7.4)
Requires-Dist: pyaml (>=23.12.0)
Requires-Dist: pydantic (>=2.11.0)
Requires-Dist: semver (>=3.0.4,<4.0.0)
Requires-Dist: tomli (>=2.2.1,<3.0.0) ; python_version < "3.11"
Requires-Dist: tomli-w (>=1.0.0)
